neatfile/__init__.py
neatfile/cli.py
neatfile/commands.py
neatfile/config.py
neatfile/constants.py
neatfile/default_config.toml
neatfile/features/__init__.py
neatfile/features/cleaning.py
neatfile/features/committing.py
neatfile/features/identify_files.py
neatfile/features/sorting.py
neatfile/models/__init__.py
neatfile/models/file.py
neatfile/models/folder.py
neatfile/models/match.py
neatfile/models/project.py
neatfile/py.typed
neatfile/utils/__init__.py
neatfile/utils/nlp.py
neatfile/utils/strings.py
neatfile/views/__init__.py
neatfile/views/prompts.py
neatfile/views/tables.py
neatfile-4.1.0.dist-info/WHEEL
neatfile-4.1.0.dist-info/entry_points.txt
neatfile-4.1.0.dist-info/METADATA
neatfile-4.1.0.dist-info/RECORD
