Metadata-Version: 2.4
Name: neatfile
Version: 4.1.0
Summary: CLI to automatically normalize and organize your files based on customizable rules.
Author: Nate Landau
Author-email: Nate Landau <neatfile@natenate.org>
License-Expression: AGPL-3.0-only
Classifier: Programming Language :: Python :: 3.11
Classifier: Programming Language :: Python :: 3.12
Classifier: Programming Language :: Python :: 3.13
Requires-Dist: cappa>=0.29.0
Requires-Dist: datefind>=0.2.1
Requires-Dist: dynaconf>=3.2.11
Requires-Dist: inflect>=7.5.0
Requires-Dist: nclutils>=2.0.0
Requires-Dist: pip>=25.1.1
Requires-Dist: questionary>=2.1.0
Requires-Dist: regex>=2024.11.6
Requires-Dist: rich>=14.1.0
Requires-Dist: spacy>=3.8.7
Requires-Dist: tzlocal>=5.3.1
Requires-Python: >=3.11, <3.14
Project-URL: Homepage, https://github.com/natelandau/neatfile
Project-URL: Repository, https://github.com/natelandau/neatfile
